cadvance/__init__.py
cadvance/__main__.py
cadvance/automation.py
cadvance/core.py
cadvance/utils.py
cadvance-0.1.0.dist-info/LICENSE
cadvance-0.1.0.dist-info/METADATA
cadvance-0.1.0.dist-info/WHEEL
cadvance-0.1.0.dist-info/entry_points.txt
cadvance-0.1.0.dist-info/top_level.txt
cadvance-0.1.0.dist-info/RECORD
