Metadata-Version: 2.2
Name: CadVance
Version: 0.1.0
Summary: A professional AutoCAD automation package
Author: Jones Peter
License: MIT
Keywords: autocad,automation,activex,comtypes
Classifier: Programming Language :: Python :: 3
Classifier: License :: OSI Approved :: MIT License
Classifier: Intended Audience :: Developers
Classifier: Intended Audience :: System Administrators
License-File: LICENSE
Requires-Dist: pywin32
Requires-Dist: colorama
Requires-Dist: psutil
Dynamic: author
Dynamic: classifier
Dynamic: description
Dynamic: description-content-type
Dynamic: keywords
Dynamic: license
Dynamic: requires-dist
Dynamic: summary
